[
    {
        "book_id":1,
        "book_type":1,
        "book_name":"线性代数",
        "book_auther":"史蒂文J.利昂",
        "book_press":"人民出版社",
        "book_price":40,
        "book_num":10
    },
    {
        "book_id":2,
        "book_type":2,
        "book_name":"格林童话",
        "book_auther":"格林兄弟",
        "book_press":"少年儿童出版社",
        "book_price":15,
        "book_num":9
    },
    {
        "book_id":3,
        "book_type":3,
        "book_name":"包法利夫人",
        "book_auther":"福楼拜",
        "book_press":"人民文学出版社",
        "book_price":34,
        "book_num":9
    },
    {
        "book_id":4,
        "book_type":4,
        "book_name":"三体全集",
        "book_auther":"刘慈欣",
        "book_press":"重庆出版社",
        "book_price":90,
        "book_num":6
    },
    {
        "book_id":5,
        "book_type":2,
        "book_name":"测试书",
        "book_auther":"数字人",
        "book_press":"少年出版社",
        "book_price":15.45,
        "book_num":9
    }
]